casampi/MPICommandClient.py
casampi/MPIEnvironment.py
casampi/MPIInterface.py
casampi/__init__.py
casampi/__main__.py
casampi/private/MPICommandServer.py
casampi/private/MPICommunicator.py
casampi/private/MPIMonitorClient.py
casampi/private/MPIMonitorServer.py
casampi/private/__init__.py
casampi/private/server_run.py
casampi/private/start_mpi.py
casampi/tests/__init__.py
casampi/tests/run.py
casampi/tests/test_casampi.py
casampi/tests/test_casampi_subset.py
casampi-0.5.9.dist-info/METADATA
casampi-0.5.9.dist-info/WHEEL
casampi-0.5.9.dist-info/top_level.txt
casampi-0.5.9.dist-info/RECORD
