Metadata-Version: 2.1
Name: casampi
Version: 0.5.9
Summary: the CASA MPI framework
Home-page: https://open-bitbucket.nrao.edu/projects/CASA/repos/casampi/browse
Download-URL: https://casa.nrao.edu/download/
Author: CASA development team
Author-email: casa-feedback@nrao.edu
Maintainer: Sandra Castro
Maintainer-email: scastro@eso.org
License: GNU Library or Lesser General Public License (LGPL)
Keywords: CASA
Requires-Dist: mpi4py >=4.0
Requires-Dist: casatools
